[
  {
    "department": "DEPT OF DEFENSE",
    "total": 620,
    "opportunities": 512,
    "wins": 108
  },
  {
    "department": "VETERANS AFFAIRS, DEPARTMENT OF",
    "total": 114,
    "opportunities": 96,
    "wins": 18
  },
  {
    "department": "INTERIOR, DEPARTMENT OF THE",
    "total": 66,
    "opportunities": 47,
    "wins": 19
  },
  {
    "department": "HOMELAND SECURITY, DEPARTMENT OF",
    "total": 47,
    "opportunities": 44,
    "wins": 3
  },
  {
    "department": "AGRICULTURE, DEPARTMENT OF",
    "total": 45,
    "opportunities": 39,
    "wins": 6
  },
  {
    "department": "HEALTH AND HUMAN SERVICES, DEPARTMENT OF",
    "total": 29,
    "opportunities": 28,
    "wins": 1
  },
  {
    "department": "STATE, DEPARTMENT OF",
    "total": 22,
    "opportunities": 22,
    "wins": 0
  },
  {
    "department": "COMMERCE, DEPARTMENT OF",
    "total": 22,
    "opportunities": 20,
    "wins": 2
  },
  {
    "department": "GENERAL SERVICES ADMINISTRATION",
    "total": 20,
    "opportunities": 13,
    "wins": 7
  },
  {
    "department": "ENERGY, DEPARTMENT OF",
    "total": 16,
    "opportunities": 13,
    "wins": 3
  },
  {
    "department": "NATIONAL AERONAUTICS AND SPACE ADMINISTRATION",
    "total": 14,
    "opportunities": 13,
    "wins": 1
  },
  {
    "department": "JUSTICE, DEPARTMENT OF",
    "total": 14,
    "opportunities": 13,
    "wins": 1
  },
  {
    "department": "TRANSPORTATION, DEPARTMENT OF",
    "total": 6,
    "opportunities": 6,
    "wins": 0
  },
  {
    "department": "ENVIRONMENTAL PROTECTION AGENCY",
    "total": 3,
    "opportunities": 3,
    "wins": 0
  },
  {
    "department": "POSTAL SERVICE",
    "total": 3,
    "opportunities": 3,
    "wins": 0
  },
  {
    "department": "TREASURY, DEPARTMENT OF THE",
    "total": 2,
    "opportunities": 2,
    "wins": 0
  },
  {
    "department": "SOCIAL SECURITY ADMINISTRATION",
    "total": 2,
    "opportunities": 2,
    "wins": 0
  },
  {
    "department": "NUCLEAR REGULATORY COMMISSION",
    "total": 2,
    "opportunities": 1,
    "wins": 1
  },
  {
    "department": "DISTRICT OF COLUMBIA COURTS",
    "total": 2,
    "opportunities": 2,
    "wins": 0
  },
  {
    "department": "LABOR, DEPARTMENT OF",
    "total": 1,
    "opportunities": 1,
    "wins": 0
  },
  {
    "department": "THE LEGISLATIVE BRANCH",
    "total": 1,
    "opportunities": 1,
    "wins": 0
  },
  {
    "department": "OFFICE OF THE DIRECTOR OF NATIONAL INTELLIGENCE",
    "total": 1,
    "opportunities": 1,
    "wins": 0
  }
]